README.rst
setup.py
httpbenchmark/__init__.py
httpbenchmark/benchmark.py
httpbenchmark/fake.py
httpbenchmark.egg-info/PKG-INFO
httpbenchmark.egg-info/SOURCES.txt
httpbenchmark.egg-info/dependency_links.txt
httpbenchmark.egg-info/requires.txt
httpbenchmark.egg-info/top_level.txt
scripts/pb