Metadata-Version: 1.1
Name: httpbenchmark
Version: 0.3.2
Summary: Python HTTP Benchmarking Tool
Home-page: https://github.com/borgstrom/httpbenchmark
Author: Evan Borgstrom
Author-email: evan@borgstrom.ca
License: Apache License, Version 2.0
Platform: UNKNOWN
Classifier: Development Status :: 3 - Alpha
Classifier: Intended Audience :: Developers
Classifier: Intended Audience :: System Administrators
Classifier: License :: OSI Approved :: Apache Software License
Classifier: Natural Language :: English
Classifier: Topic :: Software Development :: Libraries
Classifier: Topic :: Software Development :: Libraries :: Python Modules
